LICENSE
MANIFEST.in
README.md
requirements.txt
setup.py
django_saml2_sp.egg-info/PKG-INFO
django_saml2_sp.egg-info/SOURCES.txt
django_saml2_sp.egg-info/dependency_links.txt
django_saml2_sp.egg-info/requires.txt
django_saml2_sp.egg-info/top_level.txt
saml2sp/__init__.py
saml2sp/base.py
saml2sp/codex.py
saml2sp/models.py
saml2sp/saml2sp_settings.py
saml2sp/urls.py
saml2sp/views.py
saml2sp/xml_render.py
saml2sp/xml_signing.py
saml2sp/xml_templates.py
saml2sp/templates/saml2sp/base.html
saml2sp/templates/saml2sp/spssodescriptor.xml
saml2sp/templates/saml2sp/sso_complete.html
saml2sp/templates/saml2sp/sso_idp_selection.html
saml2sp/templates/saml2sp/sso_post_request.html
saml2sp/templates/saml2sp/sso_single_logout.html
saml2sp/templates/saml2sp/sso_test.html
saml2sp/tests/__init__.py