Metadata-Version: 1.0
Name: django-saml2-sp
Version: 0.2
Summary: SAML 2.0 SP for Django
Home-page: https://github.com/abhinavsingh/django-saml2
Author: John Samuel Anderson
Author-email: john@andersoninnovative.com
License: MIT
Platform: UNKNOWN
